beadsnum/__init__.py
beadsnum-2.0.1.dist-info/LICENSE
beadsnum-2.0.1.dist-info/METADATA
beadsnum-2.0.1.dist-info/WHEEL
beadsnum-2.0.1.dist-info/top_level.txt
beadsnum-2.0.1.dist-info/RECORD
