Metadata-Version: 2.1
Name: beadsnum
Version: 2.0.1
Summary: Beads nested number notation package
Home-page: https://github.com/muzudho/beads-nested-number-notation
Author: muzudho
Author-email: muzudho1@gmail.com
Project-URL: Bug Tracker, https://github.com/muzudho/beads-nested-number-notation/issues
Classifier: Programming Language :: Python :: 3
Classifier: License :: OSI Approved :: MIT License
Classifier: Operating System :: OS Independent
Requires-Python: >=3.6
License-File: LICENSE
